{
  "media_screen": "Նվագարկիչ",
  "settings_screen": "Կարգավորումներ",
  "aboutUs_screen": "Մեր Մասին",
  "rock_type": "Ճոճման Ռեժիմ",
  "rock_auto": "Ինքնուրույն ճոճում",
  "rock_state": "Միացնել ճոճումը",
  "rock_state_time": "Ակտիվացում ըստ ժամանակի",
  "off": "Անջատված",
  "solo": "Մեկանգամյա",
  "multi": "Բազմակի",
  "time_on": "Միացման ժամը",
  "time_off": "Անջատման ժամը",
  "dur": "Տևողությունը, վրկ",
  "pause": "Դադար, վրկ",
  "act_on_sound": "Ակտիվացում ձայնով",
  "act_on": "Միացնել",
  "mic_sens": "Զգայունությունը",
  "on_m_activ": "Ակտիվացում շարժումից",
  "mot_sens": "Զգայունությունը",
  "on_dur_rock": "Միացնել նվագարկիչը ճոճման ժամանակ",
  "light": "Լուսավորություն",
  "on": "Միացնել",
  "time": "Սարքի ժամանակը",
  "choose_color": "Ընտրել գույնը",
  "reconnect": "Վերամիավորվել",
  "update": "Թարմացնել",
  "versions": "Ծրագրի տարբերակ",
  "desciption_first_part": "ՄԻԼԱՐ ինքնուրույն ճոճվող խելացի օրօրոցները կդառնան Ձեր երեխայի անբաժան ընկերը։",
  "desciption_second_part": "Բնական նյութերը և հատուկ ձևավորումը կապահովեն երեխայի անվտանգությունը, իսկ ընդարձակ ֆունկցիոնալությունը կթեթևացնի ծնողների հոգսը:"
}
